streamlit_paypal/__init__.py
streamlit_paypal/frontend/dist/index.html
streamlit_paypal/frontend/dist/vite.svg
streamlit_paypal/frontend/dist/assets/index-DsOEEoh7.js
streamlit_paypal/frontend/dist/assets/index-DydtES56.css
streamlit_paypal-1.0.1.dist-info/licenses/LICENSE
tests/__init__.py
tests/test_import.py
streamlit_paypal-1.0.1.dist-info/METADATA
streamlit_paypal-1.0.1.dist-info/WHEEL
streamlit_paypal-1.0.1.dist-info/top_level.txt
streamlit_paypal-1.0.1.dist-info/RECORD
