Metadata-Version: 2.4
Name: streamlit-paypal
Version: 1.0.1
Summary: PayPal payment integration for Streamlit apps
Home-page: https://github.com/TEENLU/streamlit-paypal
Author: TEENLU
Author-email: TEENLU <ivanru372@gmail.com>
License: MIT
Project-URL: Homepage, https://github.com/TEENLU/streamlit-paypal
Project-URL: Repository, https://github.com/TEENLU/streamlit-paypal
Project-URL: Bug Tracker, https://github.com/TEENLU/streamlit-paypal/issues
Keywords: streamlit,paypal,payment,integration,component
Classifier: Development Status :: 4 - Beta
Classifier: Intended Audience :: Developers
Classifier: License :: OSI Approved :: MIT License
Classifier: Programming Language :: Python :: 3
Classifier: Programming Language :: Python :: 3.9
Classifier: Programming Language :: Python :: 3.10
Classifier: Programming Language :: Python :: 3.11
Classifier: Programming Language :: Python :: 3.12
Classifier: Topic :: Software Development :: Libraries :: Python Modules
Classifier: Topic :: Office/Business :: Financial
Classifier: Operating System :: OS Independent
Requires-Python: >=3.9
License-File: LICENSE
Requires-Dist: streamlit>=1.28.1
Requires-Dist: requests>=2.31.0
Requires-Dist: python-dotenv==1.0.1
Dynamic: author
Dynamic: home-page
Dynamic: license-file
Dynamic: requires-python
